randorth/__init__.py
randorth/randorth.py
randorth-0.0.1.dist-info/AUTHORS.rst
randorth-0.0.1.dist-info/LICENSE
randorth-0.0.1.dist-info/METADATA
randorth-0.0.1.dist-info/WHEEL
randorth-0.0.1.dist-info/top_level.txt
randorth-0.0.1.dist-info/RECORD
