Metadata-Version: 2.1
Name: randorth
Version: 0.0.1
Summary: randorth generates random basis functions.
Home-page: https://github.com/maxloge/randorth
Author: Maxime Logé
Author-email: max.loge@gmail.com
License: MIT license
Keywords: randorth
Classifier: Development Status :: 2 - Pre-Alpha
Classifier: Intended Audience :: Developers
Classifier: License :: OSI Approved :: MIT License
Classifier: Natural Language :: English
Classifier: Programming Language :: Python :: 3
Classifier: Programming Language :: Python :: 3.6
Classifier: Programming Language :: Python :: 3.7
Classifier: Programming Language :: Python :: 3.8
Requires-Python: >=3.6
License-File: LICENSE
License-File: AUTHORS.rst
